blablado/__init__.py
blablado/_assistant.py
blablado/_speak.py
blablado/_speech_recognition.py
blablado/_tools.py
blablado-0.2.2.dist-info/LICENSE
blablado-0.2.2.dist-info/METADATA
blablado-0.2.2.dist-info/WHEEL
blablado-0.2.2.dist-info/top_level.txt
blablado-0.2.2.dist-info/RECORD
