Metadata-Version: 2.1
Name: blablado
Version: 0.2.2
Summary: Use LLMs to call functions.
Home-page: https://github.com/haesleinhuepf/blablado
Author: Robert Haase
Author-email: robert.haase@uni-leipzig.de
License: BSD-3-Clause
Project-URL: Bug Tracker, https://github.com/haesleinhuepf/blablado/issues
Project-URL: Documentation, https://github.com/haesleinhuepf/blablado#README.md
Project-URL: Source Code, https://github.com/haesleinhuepf/blablado
Project-URL: User Support, https://github.com/haesleinhuepf/blablado/issues
Classifier: Development Status :: 2 - Pre-Alpha
Classifier: Intended Audience :: Developers
Classifier: License :: OSI Approved :: BSD License
Classifier: Operating System :: OS Independent
Classifier: Programming Language :: Python
Classifier: Programming Language :: Python :: 3
Classifier: Programming Language :: Python :: 3 :: Only
Classifier: Programming Language :: Python :: 3.8
Classifier: Programming Language :: Python :: 3.9
Classifier: Programming Language :: Python :: 3.10
Classifier: Topic :: Scientific/Engineering :: Image Processing
Requires-Python: >=3.9
License-File: LICENSE
Requires-Dist: numpy
Requires-Dist: openai >=1.12.0
Requires-Dist: langchain >=0.1.8
Requires-Dist: langchain-openai >=0.0.6
Provides-Extra: testing
Requires-Dist: tox ; extra == 'testing'
Requires-Dist: pytest ; extra == 'testing'
Requires-Dist: pytest-cov ; extra == 'testing'
